[
   {
      "slot": 1,
      "linkType": 0,
      "platform": "kabam.com,kongregate,steam,rotmg",
      "startTime": 1483228800000,
      "title": "New update is live!",
      "image": "https://finnishfx.github.io/tfr/1.1/UpdateNews.png",
      "endTime": 2006729600000,
      "linkDetail": "",
      "priority": 2000
   },
   {
      "slot": 2,
      "linkType": 2,
      "platform": "kabam.com,kongregate,steam,rotmg",
      "startTime": 1483228800000,
      "title": "Update Pack",
      "image": "https://finnishfx.github.io/tfr/1.0.X5.1/Reward.png",
      "endTime": 4080326400000,
      "linkDetail": "702",
      "priority": 2001
   },
   {
      "slot": 3,
      "linkType": 1,
      "platform": "kabam.com,kongregate,steam,rotmg",
      "startTime": 1483228800000,
      "title": "Join us!",
      "image": "https://finnishfx.github.io/tfr/static/DiscordBanner.png",
      "endTime": 4080326400000,
      "linkDetail": "https://discord.gg/heuxfeV",
      "priority": 2002
   },
   {
		"weight": 75,
		"title": "[IMPORTANT] Security Announcement",
		"text": "Recently there has been a lot of talk around Hacked Accounts. In order to protect your account from hackers, please make sure to: <ul><li>Never share your password or security questions with anyone, not even friends. <b>TFR Admins will never ask you for your password</b>.</li> <li>Do not download and / or use hacked client, as they can store your account name and password.</li> <li>Do not use the same password for your email, your realm account and / or other realm related websites.</li> <li>Some players will try to ask your account information for various \"services\". Do not give your account to them.</li></ul><br><b>TL;DR:</b> Accounts are being hacked due to users not being careful with their information, not due to Realm's current security system. Only you can protect your account!",
		"showAtStartup": false,
		"newsKey": "ahVzfnJlYWxtb2Z0aGVtYWRnb2RocmRyFwsSCkluR2FtZU5ld3MYgICwlazImAsM",
		"platform": "kongregate,steam,rotmg",
		"startTime": 1492041600000
	}
]
